datalake/__init__.py
datalake/datalake.py
vitesco_datalake_utils-0.1.0.dist-info/METADATA
vitesco_datalake_utils-0.1.0.dist-info/WHEEL
vitesco_datalake_utils-0.1.0.dist-info/top_level.txt
vitesco_datalake_utils-0.1.0.dist-info/RECORD
